Workbook

Sheet Cover
B2: BDC UNIVERSAL
B3: Fleet Financial Model
B4: Purchase-only Tesla-first Turo fleet, LA market
B6: Prepared for | C6: Eli Cooper · BDC Universal
B7: Operator | C7: Jared Best · Bestly LLC
B8: Date | C8: May 4, 2026
B9: Source documents | C9: EV_Fleet_Strategy_Turo.xlsx (Mar 2026) + EV_Fleet_Sourcing_Strategy.pdf (Apr 2026)
B10: Capital model | C10: Purchase only — financed at 20% down, 48-month term. NO leasing.
B12: What this model answers
B13: 1. How much capital do we need at 4, 6, 8, and 10 vehicles?
B14: 2. What does the monthly loan payment look like across realistic APRs (6.5% / 9.0% / 11.0%)?
B15: 3. What does per-vehicle profit look like at conservative / target / optimistic utilization?
B16: 4. At what fleet size does the operation cover loan payments and reach break-even?
B17: 5. What's the working-capital buffer needed to weather the first 6 months?
B18: 6. How does charging-cost mix (Supercharger vs LADWP home) affect margin?
B21: Sheets
B22: Inputs | C22: All assumptions (blue cells = your inputs). Change these, all sheets update.
B23: Fleet Scenarios | C23: Side-by-side 4 vs 6 vs 8 vs 10 vehicle comparison. THE EXEC SHEET.
B24: Unit Economics | C24: Per-vehicle revenue, cost, margin under conservative/target/optimistic.
B25: Loan Payments | C25: Monthly P&I across purchase price × APR sensitivity grid.
B26: 12-Month Cash Flow | C26: Month-by-month projection for the chosen scenario.
B27: Break-Even | C27: What it takes to cover loan + opex per vehicle.
B28: Charging | C28: Supercharger vs LADWP cost optimization.
B29: Sources | C29: Citations for every market-data figure.
B32: Color coding
B33: Blue text | C33: Hardcoded inputs / scenario knobs — edit these
B34: Black text | C34: Formulas / calculated
B35: Green text | C35: Cross-sheet references
C36: Yellow background = key assumption flagged for review

Sheet Inputs
A1: INPUTS & ASSUMPTIONS
A2: Edit the blue cells. Yellow = key assumption — review carefully.
A4: Vehicle Acquisition (Used Tesla Model Y LR, LA market)
A5: Tier | B5: Description | C5: Price ($) | D5: Notes
A6: Tier 1 — w/ legacy FSD | B6: Used 2022-2023 Model Y LR with FSD purchased outright | C6: 36000 | D6: Premium $3-5k over base. Avoids $99/mo subscription forever.
A7: Tier 2 — w/ EAP | B7: Used 2022-2023 Model Y LR with Enhanced Autopilot | C7: 32000 | D7: Qualifies for $49/mo FSD sub (half rate).
A8: Tier 3 — base (fallback) | B8: Used 2022-2023 Model Y LR, base Autopilot only | C8: 29000 | D8: Tracks LA market average.
A10: Target acquisition mix | B10: 50% Tier 2 (EAP) + 50% Tier 3 (base) — see Fleet Scenarios for unit-by-unit
A11: Blended price per vehicle | B11: =AVERAGE(C7,C8) -> 30500 | C11: (used downstream as default)
A13: Financing (purchase only — no leasing)
A14: Parameter | B14: Value | D14: Notes
A15: Down payment % | B15: 0.2 | D15: 20% standard. Higher reduces P&I but ties up capital.
A16: Loan term (months) | B16: 48 | D16: 48-month preferred for cash-flow; 60-mo possible at higher total interest.
A17: APR — excellent credit (720+) | B17: 0.065 | D17: Bankrate / NerdWallet, March 2026.
A18: APR — good credit (690-719) | B18: 0.09 | D18: Bankrate / NerdWallet, March 2026.
A19: APR — fair credit (660-689) | B19: 0.11 | D19: Bankrate / NerdWallet, March 2026.
A20: APR — base case (used in model) | B20: 0.09 | D20: Yellow = key assumption.
A22: Revenue Assumptions (Turo, LA market)
A23: Scenario | B23: Daily Rate ($) | C23: Utilization (%) | D23: Notes
A24: Conservative | B24: 65 | C24: 0.6 | D24: Low end of LA Model Y range ($61-94/day).
A25: Target | B25: 80 | C25: 0.73 | D25: Median LA Model Y, Superhost-listed.
A26: Optimistic | B26: 95 | C26: 0.85 | D26: Premium pricing, peak season, top reviews.
A28: Turo host fee | B28: 0.1 | D28: 10% take rate (operator's power-host / direct rate). Standard Turo plans run 15-25%.
A30: Per-Vehicle Monthly Operating Costs
A31: Cost | B31: Monthly ($) | D31: Notes
A32: Insurance (commercial auto) | B32: 175 | D32: Required for Turo commercial use. $150-200 range.
A33: Charging (electricity, blended) | B33: 375 | D33: Observed $0.44-0.47/kWh blended. Optimize via home L2 — see Charging sheet.
A34: Cleaning / detailing (per turnover) | B34: 250 | D34: $25-30/turnover × 8-12 turnovers. Outsource at 4+ vehicles.
A35: Car wash membership | B35: 30 | D35: Base unlimited-wash membership per vehicle (operator's preferred wash chain).
A36: Maintenance / tires reserve | B36: 65 | D36: Tires every 25-30k mi. Annual brake/A/C check.
A37: Phone mount / consumables | B37: 35 | D37: Cables, cleaning supplies, no-smoking stickers (~$0.75 ea × 2/vehicle), accessories.
A38: Depreciation reserve | B38: 225 | D38: Set aside ~$2,700/yr for replacement fund.
A39: TOTAL operating cost (excl. loan) | B39: =SUM(B32:B38) -> 1155
A41: Other
A42: FSD subscription per vehicle ($/mo) | B42: 0 | D42: Set to 0 today; activate only when robotaxi owner-program goes live in LA. Tier 2 EAP = $49/mo when activated.
A43: Working capital reserve (months per vehicle) | B43: 3 | D43: 3-month buffer. Keeps operation alive through soft season. Per-PDF recommendation.
A44: Existing fleet vehicles (already owned, no loan) | B44: 2 | D44: NOMAD (Model Y 2021) + Blue Steel (Model 3 2020). Both owned outright.

Sheet Fleet Scenarios
A1: FLEET SCENARIOS — 4 vs 6 vs 8 vs 10 vehicles
A2: All numbers monthly unless noted. Excl. existing 2 owned vehicles' contribution.
A4: Metric | B4: 4 vehicles | C4: 6 vehicles | D4: 8 vehicles | E4: 10 vehicles
A5: (adds to existing 2 owned) | B5: +2 new financed | C5: +4 new financed | D5: +6 new financed | E5: +8 new financed
A7: CAPITAL REQUIRED (one-time)
A8: Vehicles to acquire | B8: 2 | C8: 4 | D8: 6 | E8: 8
A9: Price per vehicle (blended Tier 2/3) | B9: =Inputs!B11 -> 30500 | C9: =Inputs!B11 -> 30500 | D9: =Inputs!B11 -> 30500 | E9: =Inputs!B11 -> 30500
A10: Total acquisition price | B10: =B8*B9 -> 61000 | C10: =C8*C9 -> 122000 | D10: =D8*D9 -> 183000 | E10: =E8*E9 -> 244000
A11: Down payment (20%) | B11: =B10*Inputs!B15 -> 12200 | C11: =C10*Inputs!B15 -> 24400 | D11: =D10*Inputs!B15 -> 36600 | E11: =E10*Inputs!B15 -> 48800
A12: Setup costs ($1,500/vehicle: ceramic + accessories + photos + insurance start) | B12: =B8*1500 -> 3000 | C12: =C8*1500 -> 6000 | D12: =D8*1500 -> 9000 | E12: =E8*1500 -> 12000
A13: Working capital reserve (3 mo × all vehicles) | B13: =4*Inputs!B39*Inputs!B43 -> 13860 | C13: =6*Inputs!B39*Inputs!B43 -> 20790 | D13: =8*Inputs!B39*Inputs!B43 -> 27720 | E13: =10*Inputs!B39*Inputs!B43 -> 34650
A14: TOTAL CASH NEEDED AT LAUNCH | B14: =SUM(B11:B13) -> 29060 | C14: =SUM(C11:C13) -> 51190 | D14: =SUM(D11:D13) -> 73320 | E14: =SUM(E11:E13) -> 95450
A16: MONTHLY FINANCING
A17: Loan principal per vehicle (price × 80%) | B17: =B9*(1-Inputs!B15) -> 24400 | C17: =C9*(1-Inputs!B15) -> 24400 | D17: =D9*(1-Inputs!B15) -> 24400 | E17: =E9*(1-Inputs!B15) -> 24400
A18: Monthly P&I per vehicle (PMT @ base APR, 48mo) | B18: =PMT(Inputs!B20/12,Inputs!B16,-B17) -> 607.19503 | C18: =PMT(Inputs!B20/12,Inputs!B16,-C17) -> 607.19503 | D18: =PMT(Inputs!B20/12,Inputs!B16,-D17) -> 607.19503 | E18: =PMT(Inputs!B20/12,Inputs!B16,-E17) -> 607.19503
A19: Total monthly loan payment (× new vehicles) | B19: =B8*B18 -> 1214.3901 | C19: =C8*C18 -> 2428.7801 | D19: =D8*D18 -> 3643.1702 | E19: =E8*E18 -> 4857.5603
A21: MONTHLY REVENUE (Target case)
A22: Net revenue per vehicle (after Turo 25% fee) | B22: =Inputs!B25*Inputs!C25*30*(1-Inputs!B28) -> 1576.8 | C22: =Inputs!B25*Inputs!C25*30*(1-Inputs!B28) -> 1576.8 | D22: =Inputs!B25*Inputs!C25*30*(1-Inputs!B28) -> 1576.8 | E22: =Inputs!B25*Inputs!C25*30*(1-Inputs!B28) -> 1576.8
A23: Fleet net revenue (all vehicles) | B23: =4*B22 -> 6307.2 | C23: =6*C22 -> 9460.8 | D23: =8*D22 -> 12614.4 | E23: =10*E22 -> 15768
A25: MONTHLY OPEX
A26: Operating cost per vehicle (Inputs!B39) | B26: =Inputs!B39 -> 1155 | C26: =Inputs!B39 -> 1155 | D26: =Inputs!B39 -> 1155 | E26: =Inputs!B39 -> 1155
A27: Fleet opex (all vehicles) | B27: =4*B26 -> 4620 | C27: =6*C26 -> 6930 | D27: =8*D26 -> 9240 | E27: =10*E26 -> 11550
A29: MONTHLY NET (Target case)
A30: Net revenue (line 23) | B30: =B23 -> 6307.2 | C30: =C23 -> 9460.8 | D30: =D23 -> 12614.4 | E30: =E23 -> 15768
A31: Less: opex (line 27) | B31: =-B27 -> -4620 | C31: =-C27 -> -6930 | D31: =-D27 -> -9240 | E31: =-E27 -> -11550
A32: Less: loan payment (line 19) | B32: =-B19 -> -1214.3901 | C32: =-C19 -> -2428.7801 | D32: =-D19 -> -3643.1702 | E32: =-E19 -> -4857.5603
A33: MONTHLY NET PROFIT | B33: =SUM(B30:B32) -> 472.80993 | C33: =SUM(C30:C32) -> 102.01986 | D33: =SUM(D30:D32) -> -268.7702 | E33: =SUM(E30:E32) -> -639.56027
A34: Annualized net (× 12) | B34: =B33*12 -> 5673.7192 | C34: =C33*12 -> 1224.2384 | D34: =D33*12 -> -3225.2424 | E34: =E33*12 -> -7674.7233
A36: SENSITIVITY (alt scenarios)
A37: Net at CONSERVATIVE utilization | B37: =4*Inputs!B24*Inputs!C24*30*(1-Inputs!B28)-4*Inputs!B39-B19 -> -1622.3901 | C37: =6*Inputs!B24*Inputs!C24*30*(1-Inputs!B28)-6*Inputs!B39-C19 -> -3040.7801 | D37: =8*Inputs!B24*Inputs!C24*30*(1-Inputs!B28)-8*Inputs!B39-D19 -> -4459.1702 | E37: =10*Inputs!B24*Inputs!C24*30*(1-Inputs!B28)-10*Inputs!B39-E19 -> -5877.5603
A38: Net at OPTIMISTIC utilization | B38: =4*Inputs!B26*Inputs!C26*30*(1-Inputs!B28)-4*Inputs!B39-B19 -> 2886.6099 | C38: =6*Inputs!B26*Inputs!C26*30*(1-Inputs!B28)-6*Inputs!B39-C19 -> 3722.7199 | D38: =8*Inputs!B26*Inputs!C26*30*(1-Inputs!B28)-8*Inputs!B39-D19 -> 4558.8298 | E38: =10*Inputs!B26*Inputs!C26*30*(1-Inputs!B28)-10*Inputs!B39-E19 -> 5394.9397
A40: Eli's break-even target | B40: Month 4-5-6 from launch (per call discussion)
A41: Working capital buffer concern | B41: $200k cushion for first 6 months — line 13 above shows actual reserve at each scenario

Sheet Unit Economics
A1: PER-VEHICLE UNIT ECONOMICS
A2: Single financed vehicle, 48-mo loan @ base APR, blended Tier 2/3 price.
A4: Line item | B4: Conservative | C4: Target | D4: Optimistic | E4: Notes
A5: Daily rate | B5: =Inputs!B24 -> 65 | C5: =Inputs!B25 -> 80 | D5: =Inputs!B26 -> 95
A6: Utilization | B6: =Inputs!C24 -> 0.6 | C6: =Inputs!C25 -> 0.73 | D6: =Inputs!C26 -> 0.85
A7: Days booked / month (= util × 30) | B7: =B6*30 -> 18 | C7: =C6*30 -> 21.9 | D7: =D6*30 -> 25.5
A8: Gross trip revenue | B8: =B5*B7 -> 1170 | C8: =C5*C7 -> 1752 | D8: =D5*D7 -> 2422.5
A9: Less: Turo 25% host fee | B9: =-B8*Inputs!B28 -> -117 | C9: =-C8*Inputs!B28 -> -175.2 | D9: =-D8*Inputs!B28 -> -242.25
A10: NET BOOKING REVENUE | B10: =B8+B9 -> 1053 | C10: =C8+C9 -> 1576.8 | D10: =D8+D9 -> 2180.25
A12: COSTS (per vehicle, monthly)
A13: Insurance | B13: =Inputs!B32 -> 175 | C13: =Inputs!B32 -> 175 | D13: =Inputs!B32 -> 175
A14: Charging | B14: =Inputs!B33 -> 375 | C14: =Inputs!B33 -> 375 | D14: =Inputs!B33 -> 375
A15: Cleaning | B15: =Inputs!B34 -> 250 | C15: =Inputs!B34 -> 250 | D15: =Inputs!B34 -> 250
A16: Car wash membership | B16: =Inputs!B35 -> 30 | C16: =Inputs!B35 -> 30 | D16: =Inputs!B35 -> 30
A17: Maintenance | B17: =Inputs!B36 -> 65 | C17: =Inputs!B36 -> 65 | D17: =Inputs!B36 -> 65
A18: Phone / consumables (incl. no-smoking stickers) | B18: =Inputs!B37 -> 35 | C18: =Inputs!B37 -> 35 | D18: =Inputs!B37 -> 35
A19: Depreciation reserve | B19: =Inputs!B38 -> 225 | C19: =Inputs!B38 -> 225 | D19: =Inputs!B38 -> 225
A20: Loan P&I (financed @ base APR, 48-mo) | B20: =PMT(Inputs!B20/12,Inputs!B16,-Inputs!B11*(1-Inputs!B15)) -> 607.19503 | C20: =PMT(Inputs!B20/12,Inputs!B16,-Inputs!B11*(1-Inputs!B15)) -> 607.19503 | D20: =PMT(Inputs!B20/12,Inputs!B16,-Inputs!B11*(1-Inputs!B15)) -> 607.19503
A21: TOTAL COSTS (incl. loan) | B21: =SUM(B13:B20) -> 1762.195 | C21: =SUM(C13:C20) -> 1762.195 | D21: =SUM(D13:D20) -> 1762.195
A23: NET MARGIN $ | B23: =B10-B21 -> -709.19503 | C23: =C10-C21 -> -185.39503 | D23: =D10-D21 -> 418.05497
A24: NET MARGIN % | B24: =IFERROR(B23/B10,0) -> -0.67349956 | C24: =IFERROR(C23/C10,0) -> -0.11757676 | D24: =IFERROR(D23/D10,0) -> 0.19174634
A26: OWNED-VEHICLE COMPARISON (no loan — NOMAD/Blue Steel)
A27: Net revenue (same as line 10) | B27: =B10 -> 1053 | C27: =C10 -> 1576.8 | D27: =D10 -> 2180.25
A28: Costs ex-loan | B28: =B21-B20 -> 1155 | C28: =C21-C20 -> 1155 | D28: =D21-D20 -> 1155
A29: OWNED NET MARGIN $ | B29: =B27-B28 -> -102 | C29: =C27-C28 -> 421.8 | D29: =D27-D28 -> 1025.25
A30: OWNED NET MARGIN % | B30: =IFERROR(B29/B27,0) -> -0.096866097 | C30: =IFERROR(C29/C27,0) -> 0.26750381 | D30: =IFERROR(D29/D27,0) -> 0.47024424
A32: HARD TRUTH
A33: At target utilization a newly financed vehicle's margin depends heavily on Turo take rate.
A34: At your 10% rate, daily rate × utilization break-even is much lower than the 25% case.
A35: Levers: daily rate, utilization, charging mix (every 10% home-shift saves ~$35/vehicle/mo), loan payoff.
A36: The existing 2 owned vehicles ARE profitable — see line 29 — and subsidize newly added units.

Sheet Loan Payments
A1: LOAN PAYMENT SENSITIVITY
A2: Monthly P&I across purchase price × APR. 20% down, 48-month term.
A4: Purchase price | B4: 6.00% | C4: 6.50% | D4: 7.50% | E4: 9.00% | F4: 10.50% | G4: 11.00%
A5: 27000 | B5: =PMT(0.06/12,Inputs!B16,-A5*(1-Inputs!B15)) -> 507.27663 | C5: =PMT(0.065/12,Inputs!B16,-A5*(1-Inputs!B15)) -> 512.24298 | D5: =PMT(0.075/12,Inputs!B16,-A5*(1-Inputs!B15)) -> 522.26428 | E5: =PMT(0.09/12,Inputs!B16,-A5*(1-Inputs!B15)) -> 537.51692 | F5: =PMT(0.105/12,Inputs!B16,-A5*(1-Inputs!B15)) -> 553.033 | G5: =PMT(0.11/12,Inputs!B16,-A5*(1-Inputs!B15)) -> 558.26329
A6: 30000 | B6: =PMT(0.06/12,Inputs!B16,-A6*(1-Inputs!B15)) -> 563.6407 | C6: =PMT(0.065/12,Inputs!B16,-A6*(1-Inputs!B15)) -> 569.15887 | D6: =PMT(0.075/12,Inputs!B16,-A6*(1-Inputs!B15)) -> 580.29365 | E6: =PMT(0.09/12,Inputs!B16,-A6*(1-Inputs!B15)) -> 597.24102 | F6: =PMT(0.105/12,Inputs!B16,-A6*(1-Inputs!B15)) -> 614.48111 | G6: =PMT(0.11/12,Inputs!B16,-A6*(1-Inputs!B15)) -> 620.29254
A7: 32000 | B7: =PMT(0.06/12,Inputs!B16,-A7*(1-Inputs!B15)) -> 601.21674 | C7: =PMT(0.065/12,Inputs!B16,-A7*(1-Inputs!B15)) -> 607.10279 | D7: =PMT(0.075/12,Inputs!B16,-A7*(1-Inputs!B15)) -> 618.97989 | E7: =PMT(0.09/12,Inputs!B16,-A7*(1-Inputs!B15)) -> 637.05708 | F7: =PMT(0.105/12,Inputs!B16,-A7*(1-Inputs!B15)) -> 655.44652 | G7: =PMT(0.11/12,Inputs!B16,-A7*(1-Inputs!B15)) -> 661.64538
A8: 35000 | B8: =PMT(0.06/12,Inputs!B16,-A8*(1-Inputs!B15)) -> 657.58081 | C8: =PMT(0.065/12,Inputs!B16,-A8*(1-Inputs!B15)) -> 664.01868 | D8: =PMT(0.075/12,Inputs!B16,-A8*(1-Inputs!B15)) -> 677.00925 | E8: =PMT(0.09/12,Inputs!B16,-A8*(1-Inputs!B15)) -> 696.78119 | F8: =PMT(0.105/12,Inputs!B16,-A8*(1-Inputs!B15)) -> 716.89463 | G8: =PMT(0.11/12,Inputs!B16,-A8*(1-Inputs!B15)) -> 723.67463
A9: 38000 | B9: =PMT(0.06/12,Inputs!B16,-A9*(1-Inputs!B15)) -> 713.94488 | C9: =PMT(0.065/12,Inputs!B16,-A9*(1-Inputs!B15)) -> 720.93457 | D9: =PMT(0.075/12,Inputs!B16,-A9*(1-Inputs!B15)) -> 735.03862 | E9: =PMT(0.09/12,Inputs!B16,-A9*(1-Inputs!B15)) -> 756.50529 | F9: =PMT(0.105/12,Inputs!B16,-A9*(1-Inputs!B15)) -> 778.34274 | G9: =PMT(0.11/12,Inputs!B16,-A9*(1-Inputs!B15)) -> 785.70389
A10: 41630 | B10: =PMT(0.06/12,Inputs!B16,-A10*(1-Inputs!B15)) -> 782.14541 | C10: =PMT(0.065/12,Inputs!B16,-A10*(1-Inputs!B15)) -> 789.80279 | D10: =PMT(0.075/12,Inputs!B16,-A10*(1-Inputs!B15)) -> 805.25415 | E10: =PMT(0.09/12,Inputs!B16,-A10*(1-Inputs!B15)) -> 828.77145 | F10: =PMT(0.105/12,Inputs!B16,-A10*(1-Inputs!B15)) -> 852.69496 | G10: =PMT(0.11/12,Inputs!B16,-A10*(1-Inputs!B15)) -> 860.75929
A11: 48990 | B11: =PMT(0.06/12,Inputs!B16,-A11*(1-Inputs!B15)) -> 920.42526 | C11: =PMT(0.065/12,Inputs!B16,-A11*(1-Inputs!B15)) -> 929.43644 | D11: =PMT(0.075/12,Inputs!B16,-A11*(1-Inputs!B15)) -> 947.61952 | E11: =PMT(0.09/12,Inputs!B16,-A11*(1-Inputs!B15)) -> 975.29458 | F11: =PMT(0.105/12,Inputs!B16,-A11*(1-Inputs!B15)) -> 1003.4477 | G11: =PMT(0.11/12,Inputs!B16,-A11*(1-Inputs!B15)) -> 1012.9377
A13: Down payment (20% of price column) | B13: =A5*Inputs!B15 -> 5400 | C13: =A6*Inputs!B15 -> 6000 | D13: =A7*Inputs!B15 -> 6400 | E13: =A8*Inputs!B15 -> 7000 | F13: =A9*Inputs!B15 -> 7600 | G13: =A10*Inputs!B15 -> 8326 | H13: =A11*Inputs!B15 -> 9798
A15: Reading the table
A16: Eli's call discussion: monthly loan payment 'could be $8000, $9000, $10,000 or $13,000'.
A17: At 6 vehicles × $35K used Tesla @ 9% APR (cell E8), per-vehicle is ~$700 → fleet total ~$4,200/mo.
A18: At 10 vehicles × $35K @ 9% APR, fleet total is 10 × that = ~$7,000/mo (fewer than Eli's high-end estimate, well within range).
A19: Eli's $13K/mo number lands if buying mix of new 2026 Model Y Premium ($48,990) at 11% APR — see G11 ($1,229/mo × 10 = $12,290/mo).

Sheet 12-Month Cash Flow
A1: 12-MONTH CASH FLOW PROJECTION
A2: Pick your scenario in B4 below. All months computed from Inputs.
A4: Scenario | B4: 6 | C4: ← number of vehicles (try 4, 6, 8, 10)
A5: New financed vehicles | B5: =B4-Inputs!B44 -> 4
A7: Month → | B7: M1 | C7: M2 | D7: M3 | E7: M4 | F7: M5 | G7: M6 | H7: M7 | I7: M8 | J7: M9 | K7: M10 | L7: M11 | M7: M12 | N7: Total
A8: Utilization ramp | B8: 0.4 | C8: 0.5 | D8: 0.6 | E8: 0.65 | F8: 0.7 | G8: 0.73 | H8: 0.73 | I8: 0.73 | J8: 0.73 | K8: 0.73 | L8: 0.73 | M8: 0.73
A9: Daily rate (target) | B9: =Inputs!B25 -> 80 | C9: =Inputs!B25 -> 80 | D9: =Inputs!B25 -> 80 | E9: =Inputs!B25 -> 80 | F9: =Inputs!B25 -> 80 | G9: =Inputs!B25 -> 80 | H9: =Inputs!B25 -> 80 | I9: =Inputs!B25 -> 80 | J9: =Inputs!B25 -> 80 | K9: =Inputs!B25 -> 80 | L9: =Inputs!B25 -> 80 | M9: =Inputs!B25 -> 80
A10: Net revenue per vehicle | B10: =B8*B9*30*(1-Inputs!B28) -> 864 | C10: =C8*C9*30*(1-Inputs!B28) -> 1080 | D10: =D8*D9*30*(1-Inputs!B28) -> 1296 | E10: =E8*E9*30*(1-Inputs!B28) -> 1404 | F10: =F8*F9*30*(1-Inputs!B28) -> 1512 | G10: =G8*G9*30*(1-Inputs!B28) -> 1576.8 | H10: =H8*H9*30*(1-Inputs!B28) -> 1576.8 | I10: =I8*I9*30*(1-Inputs!B28) -> 1576.8 | J10: =J8*J9*30*(1-Inputs!B28) -> 1576.8 | K10: =K8*K9*30*(1-Inputs!B28) -> 1576.8 | L10: =L8*L9*30*(1-Inputs!B28) -> 1576.8 | M10: =M8*M9*30*(1-Inputs!B28) -> 1576.8
A11: Fleet net revenue | B11: =B10*$B$4 -> 5184 | C11: =C10*$B$4 -> 6480 | D11: =D10*$B$4 -> 7776 | E11: =E10*$B$4 -> 8424 | F11: =F10*$B$4 -> 9072 | G11: =G10*$B$4 -> 9460.8 | H11: =H10*$B$4 -> 9460.8 | I11: =I10*$B$4 -> 9460.8 | ... M11: =M10*$B$4 -> 9460.8
A13: Fleet opex | B13: =-$B$4*Inputs!B39 -> -6930 | C13: =-$B$4*Inputs!B39 -> -6930 | D13: =-$B$4*Inputs!B39 -> -6930 | E13: =-$B$4*Inputs!B39 -> -6930 | F13: =-$B$4*Inputs!B39 -> -6930 | G13: =-$B$4*Inputs!B39 -> -6930 | H13: =-$B$4*Inputs!B39 -> -6930 | I13: =-$B$4*Inputs!B39 -> -6930 | J13: =-$B$4*Inputs!B39 -> -6930 | K13: =-$B$4*Inputs!B39 -> -6930 | L13: =-$B$4*Inputs!B39 -> -6930 | M13: =-$B$4*Inputs!B39 -> -6930
A14: Fleet loan payment | B14: =-$B$5*PMT(Inputs!B20/12,Inputs!B16,-Inputs!B11*(1-Inputs!B15)) -> -2428.7801 | C14: =-$B$5*PMT(Inputs!B20/12,Inputs!B16,-Inputs!B11*(1-Inputs!B15)) -> -2428.7801 | D14: =-$B$5*PMT(Inputs!B20/12,Inputs!B16,-Inputs!B11*(1-Inputs!B15)) -> -2428.7801 | E14: =-$B$5*PMT(Inputs!B20/12,Inputs!B16,-Inputs!B11*(1-Inputs!B15)) -> -2428.7801 | F14: =-$B$5*PMT(Inputs!B20/12,Inputs!B16,-Inputs!B11*(1-Inputs!B15)) -> -2428.7801 | G14: =-$B$5*PMT(Inputs!B20/12,Inputs!B16,-Inputs!B11*(1-Inputs!B15)) -> -2428.7801 | H14: =-$B$5*PMT(Inputs!B20/12,Inputs!B16,-Inputs!B11*(1-Inputs!B15)) -> -2428.7801 | I14: =-$B$5*PMT(Inputs!B20/12,Inputs!B16,-Inputs!B11*(1-Inputs!B15)) -> -2428.7801 | J14: =-$B$5*PMT(Inputs!B20/12,Inputs!B16,-Inputs!B11*(1-Inputs!B15)) -> -2428.7801 | K14: =-$B$5*PMT(Inputs!B20/12,Inputs!B16,-Inputs!B11*(1-Inputs!B15)) -> -2428.7801 | L14: =-$B$5*PMT(Inputs!B20/12,Inputs!B16,-Inputs!B11*(1-Inputs!B15)) -> -2428.7801 | M14: =-$B$5*PMT(Inputs!B20/12,Inputs!B16,-Inputs!B11*(1-Inputs!B15)) -> -2428.7801
A15: MONTHLY NET | B15: =SUM(B11+B13+B14) -> -4174.7801 | C15: =SUM(C11+C13+C14) -> -2878.7801 | D15: =SUM(D11+D13+D14) -> -1582.7801 | E15: =SUM(E11+E13+E14) -> -934.78014 | F15: =SUM(F11+F13+F14) -> -286.78014 | G15: =SUM(G11+G13+G14) -> 102.01986 | H15: =SUM(H11+H13+H14) -> 102.01986 | I15: =SUM(I11+I13+I14) -> 102.01986 | ... M15: =SUM(M11+M13+M14) -> 102.01986 | N15: =SUM(B15:M15) -> -9143.7616
A16: CUMULATIVE NET | B16: =B15 -> -4174.7801 | C16: =B16+C15 -> -7053.5603 | D16: =C16+D15 -> -8636.3404 | E16: =D16+E15 -> -9571.1205 | F16: =E16+F15 -> -9857.9007 | G16: =F16+G15 -> -9755.8808 | H16: =G16+H15 -> -9653.8609 | I16: =H16+I15 -> -9551.8411 | J16: =I16+J15 -> -9449.8212 | ... M16: =L16+M15 -> -9143.7616
A18: Break-even month (cumulative net flips positive) | B18: =IFERROR(MATCH(TRUE(),INDEX(B16:M16>0,0),0),"Not within 12 months") -> Not within 12 months
A20: Note: this projection excludes the existing 2 owned vehicles' contribution (~$1,000/mo each at target).
A21: Add ~$24,000 to the 12-month total to include them.

Sheet Break-Even
A1: BREAK-EVEN ANALYSIS
A2: Daily rate × utilization required to cover loan + opex per financed vehicle.
A4: Total monthly cost per financed vehicle (loan + opex) | B4: =Inputs!B39+PMT(Inputs!B20/12,Inputs!B16,-Inputs!B11*(1-Inputs!B15)) -> 1762.195
A5: Required NET monthly revenue | B5: =B4 -> 1762.195
A6: Required GROSS revenue (before Turo 25%) | B6: =B5/(1-Inputs!B28) -> 1957.9945
A8: NET MONTHLY PROFIT BY DAILY RATE × UTILIZATION (financed vehicle)
A10: Daily rate ↓ / Util → | B10: 0.55 | C10: 0.6 | D10: 0.65 | E10: 0.7 | F10: 0.75 | G10: 0.8 | H10: 0.85 | I10: 0.9
A11: 60 | B11: =A11*0.55*30*(1-Inputs!B28)-$B$4 -> -871.19503 | C11: =A11*0.6*30*(1-Inputs!B28)-$B$4 -> -790.19503 | D11: =A11*0.65*30*(1-Inputs!B28)-$B$4 -> -709.19503 | E11: =A11*0.7*30*(1-Inputs!B28)-$B$4 -> -628.19503 | F11: =A11*0.75*30*(1-Inputs!B28)-$B$4 -> -547.19503 | G11: =A11*0.8*30*(1-Inputs!B28)-$B$4 -> -466.19503 | H11: =A11*0.85*30*(1-Inputs!B28)-$B$4 -> -385.19503 | I11: =A11*0.9*30*(1-Inputs!B28)-$B$4 -> -304.19503
A12: 70 | B12: =A12*0.55*30*(1-Inputs!B28)-$B$4 -> -722.69503 | C12: =A12*0.6*30*(1-Inputs!B28)-$B$4 -> -628.19503 | D12: =A12*0.65*30*(1-Inputs!B28)-$B$4 -> -533.69503 | E12: =A12*0.7*30*(1-Inputs!B28)-$B$4 -> -439.19503 | F12: =A12*0.75*30*(1-Inputs!B28)-$B$4 -> -344.69503 | G12: =A12*0.8*30*(1-Inputs!B28)-$B$4 -> -250.19503 | H12: =A12*0.85*30*(1-Inputs!B28)-$B$4 -> -155.69503 | I12: =A12*0.9*30*(1-Inputs!B28)-$B$4 -> -61.195034
A13: 80 | B13: =A13*0.55*30*(1-Inputs!B28)-$B$4 -> -574.19503 | C13: =A13*0.6*30*(1-Inputs!B28)-$B$4 -> -466.19503 | D13: =A13*0.65*30*(1-Inputs!B28)-$B$4 -> -358.19503 | E13: =A13*0.7*30*(1-Inputs!B28)-$B$4 -> -250.19503 | F13: =A13*0.75*30*(1-Inputs!B28)-$B$4 -> -142.19503 | G13: =A13*0.8*30*(1-Inputs!B28)-$B$4 -> -34.195034 | H13: =A13*0.85*30*(1-Inputs!B28)-$B$4 -> 73.804966 | I13: =A13*0.9*30*(1-Inputs!B28)-$B$4 -> 181.80497
A14: 90 | B14: =A14*0.55*30*(1-Inputs!B28)-$B$4 -> -425.69503 | C14: =A14*0.6*30*(1-Inputs!B28)-$B$4 -> -304.19503 | D14: =A14*0.65*30*(1-Inputs!B28)-$B$4 -> -182.69503 | E14: =A14*0.7*30*(1-Inputs!B28)-$B$4 -> -61.195034 | F14: =A14*0.75*30*(1-Inputs!B28)-$B$4 -> 60.304966 | G14: =A14*0.8*30*(1-Inputs!B28)-$B$4 -> 181.80497 | H14: =A14*0.85*30*(1-Inputs!B28)-$B$4 -> 303.30497 | I14: =A14*0.9*30*(1-Inputs!B28)-$B$4 -> 424.80497
A15: 100 | B15: =A15*0.55*30*(1-Inputs!B28)-$B$4 -> -277.19503 | C15: =A15*0.6*30*(1-Inputs!B28)-$B$4 -> -142.19503 | D15: =A15*0.65*30*(1-Inputs!B28)-$B$4 -> -7.1950339 | E15: =A15*0.7*30*(1-Inputs!B28)-$B$4 -> 127.80497 | F15: =A15*0.75*30*(1-Inputs!B28)-$B$4 -> 262.80497 | G15: =A15*0.8*30*(1-Inputs!B28)-$B$4 -> 397.80497 | H15: =A15*0.85*30*(1-Inputs!B28)-$B$4 -> 532.80497 | I15: =A15*0.9*30*(1-Inputs!B28)-$B$4 -> 667.80497
A16: 110 | B16: =A16*0.55*30*(1-Inputs!B28)-$B$4 -> -128.69503 | C16: =A16*0.6*30*(1-Inputs!B28)-$B$4 -> 19.804966 | D16: =A16*0.65*30*(1-Inputs!B28)-$B$4 -> 168.30497 | E16: =A16*0.7*30*(1-Inputs!B28)-$B$4 -> 316.80497 | F16: =A16*0.75*30*(1-Inputs!B28)-$B$4 -> 465.30497 | G16: =A16*0.8*30*(1-Inputs!B28)-$B$4 -> 613.80497 | H16: =A16*0.85*30*(1-Inputs!B28)-$B$4 -> 762.30497 | I16: =A16*0.9*30*(1-Inputs!B28)-$B$4 -> 910.80497
A17: 120 | B17: =A17*0.55*30*(1-Inputs!B28)-$B$4 -> 19.804966 | C17: =A17*0.6*30*(1-Inputs!B28)-$B$4 -> 181.80497 | D17: =A17*0.65*30*(1-Inputs!B28)-$B$4 -> 343.80497 | E17: =A17*0.7*30*(1-Inputs!B28)-$B$4 -> 505.80497 | F17: =A17*0.75*30*(1-Inputs!B28)-$B$4 -> 667.80497 | G17: =A17*0.8*30*(1-Inputs!B28)-$B$4 -> 829.80497 | H17: =A17*0.85*30*(1-Inputs!B28)-$B$4 -> 991.80497 | I17: =A17*0.9*30*(1-Inputs!B28)-$B$4 -> 1153.805
A20: Reading the table
A21: Green cells = positive monthly profit. The financed vehicle is in the green at $90+/day and 80%+ utilization.
A22: LA peak season (Jun-Sep) routinely supports those levels for Superhost-listed Model Y. Off-season tightens.
A23: The two existing OWNED vehicles run profitable across nearly all cells — see Unit Economics line 28.

Sheet Charging
A1: CHARGING COST OPTIMIZATION
A2: Every 10% shift from Supercharger to home L2 saves ~$35/vehicle/mo.
A4: Source | B4: Rate ($/kWh) | C4: Notes
A5: LADWP residential (LA) | B5: 0.225 | C5: 2026 residential schedule. Best rate.
A6: Tesla Supercharger LA off-peak (12-8 AM) | B6: 0.34 | C6: Industrial St, LA
A7: Tesla Supercharger LA standard | B7: 0.45 | C7: Venice Blvd, LA — owner rate
A8: Tesla Supercharger LA peak | B8: 0.63 | C8: Industrial St, LA peak
A9: Non-Tesla EV at Supercharger | B9: 0.64 | C9: Higher rate for non-Tesla via NACS.
A12: Monthly cost based on mix (per vehicle)
A14: Monthly kWh consumed per vehicle (current pace) | B14: 800 | C14: (NOMAD + Blue Steel avg ~810 kWh/mo per PDF data)
A16: Mix (% home-charged) | B16: 0.3 | C16: ← change this; rest of column auto-updates
A17: % Supercharged | B17: =1-B16 -> 0.7
A19: Home charging cost (LADWP) | B19: =B14*B16*B5 -> 54
A20: Supercharger cost (LA standard rate) | B20: =B14*B17*B7 -> 252
A21: TOTAL monthly charging cost per vehicle | B21: =B19+B20 -> 306
A23: Compared to current (Inputs!B33) | B23: =Inputs!B33-B21 -> 69 | C23: ← positive = SAVINGS vs. current blended rate
A25: MIX SENSITIVITY (per vehicle)
A26: % home-charged | B26: Monthly cost | C26: Savings vs current | D26: Annual savings
A27: 0 | B27: =B$14*A27*B$5+B$14*(1-A27)*B$7 -> 360 | C27: =Inputs!B33-B27 -> 15 | D27: =C27*12 -> 180
A28: 0.1 | B28: =B$14*A28*B$5+B$14*(1-A28)*B$7 -> 342 | C28: =Inputs!B33-B28 -> 33 | D28: =C28*12 -> 396
A29: 0.2 | B29: =B$14*A29*B$5+B$14*(1-A29)*B$7 -> 324 | C29: =Inputs!B33-B29 -> 51 | D29: =C29*12 -> 612
A30: 0.3 | B30: =B$14*A30*B$5+B$14*(1-A30)*B$7 -> 306 | C30: =Inputs!B33-B30 -> 69 | D30: =C30*12 -> 828
A31: 0.4 | B31: =B$14*A31*B$5+B$14*(1-A31)*B$7 -> 288 | C31: =Inputs!B33-B31 -> 87 | D31: =C31*12 -> 1044
A32: 0.5 | B32: =B$14*A32*B$5+B$14*(1-A32)*B$7 -> 270 | C32: =Inputs!B33-B32 -> 105 | D32: =C32*12 -> 1260
A33: 0.6 | B33: =B$14*A33*B$5+B$14*(1-A33)*B$7 -> 252 | C33: =Inputs!B33-B33 -> 123 | D33: =C33*12 -> 1476
A34: 0.7 | B34: =B$14*A34*B$5+B$14*(1-A34)*B$7 -> 234 | C34: =Inputs!B33-B34 -> 141 | D34: =C34*12 -> 1692
A35: 0.8 | B35: =B$14*A35*B$5+B$14*(1-A35)*B$7 -> 216 | C35: =Inputs!B33-B35 -> 159 | D35: =C35*12 -> 1908
A36: 0.9 | B36: =B$14*A36*B$5+B$14*(1-A36)*B$7 -> 198 | C36: =Inputs!B33-B36 -> 177 | D36: =C36*12 -> 2124
A37: 1 | B37: =B$14*A37*B$5+B$14*(1-A37)*B$7 -> 180 | C37: =Inputs!B33-B37 -> 195 | D37: =C37*12 -> 2340
A39: L2 charger ROI
A40: Second L2 EVSE install cost: ~$1,000-1,500
A41: At 50% home mix savings (row 32): ~$80/vehicle/mo × 4 vehicles = $320/mo savings = ~5-month payback

Sheet Sources
A1: MARKET DATA SOURCES
A2: All non-derived numbers in this model are sourced from these documents and public references.
A4: Topic | B4: Source(s) | C4: Date
A5: Used 2022-2023 Model Y LR prices — LA market | B5: Edmunds, CarGurus, Cars.com, Carvana, CARFAX, TrueCar | C5: April 2026
A6: New 2026 Model Y MSRP | B6: Tesla.com configurator; KBB; Edmunds | C6: April 2026
A7: Auto loan rates (used + new) | B7: Edmunds (Mar 2026), Cox Automotive (Feb 2026), Bankrate, NerdWallet | C7: Feb-Mar 2026
A8: Tesla FSD subscription pricing | B8: Tesla Support; InsideEVs; NotATeslaApp; Teslarati | C8: April 2026
A9: Tesla battery warranty (Model Y LR 8yr/120K mi) | B9: Tesla Vehicle Warranty; Recharged 2026 guide | C9: 2026
A10: LADWP residential rates ($0.225/kWh) | B10: LADWP; Office of Public Accountability | C10: 2026
A11: Tesla Supercharger LA rates ($0.34-0.63/kWh) | B11: Tesla.com (Industrial St, Venice Blvd LA sites) | C11: April 2026
A12: Turo LA Model Y daily rates ($61-94) | B12: Turo public listings (West Hollywood, Burbank, Van Nuys) | C12: April 2026
A13: Robotaxi deployment status | B13: Tesla investor communications; CNBC; InsideEVs | C13: Q1 2026
A14: Source workbook — multi-vehicle scenario structure | B14: EV_Fleet_Strategy_Turo.xlsx (Google Drive) | C14: March 2026
A15: Source PDF — purchase-only thesis + unit economics | B15: EV_Fleet_Sourcing_Strategy.pdf (Google Drive / Bestly Cloud) | C15: April 2026
A18: Note on robotaxi revenue
A19: Robotaxi revenue is INTENTIONALLY EXCLUDED from this model. The Tesla owner-fleet program is not yet live.
A20: Acquisition decisions should be priced on Turo P&L alone; treat robotaxi as forward-looking optionality.
A21: When the owner program opens, re-run Unit Economics + Fleet Scenarios with current robotaxi data.
A23: Note on leasing
A24: Leasing is INTENTIONALLY EXCLUDED. Three reasons (per source PDF):
A25: (1) Tesla direct leases prohibit commercial / peer-to-peer rental use — repossession risk.
A26: (2) Operation already paces 30,000+ mi/vehicle/year — exceeds every standard lease allowance.
A27: (3) Only purchased vehicles are eligible for Tesla's forthcoming owner-robotaxi network.
